[
  {
    "name": "Klinge des Unsterblichen",
    "description": "Sagenumwobene Klinge, die niemals ihre Schärfe verliert.",
    "img-path": "imgs/items/weapon/immortal_blade.webp",
    "price": 1500,
    "armor-slot": "weapon-1",
    "tier": "5",
    "weapon-type": "schnitt",
    "hands": "1",
    "requirement": {
      "stat": "strength",
      "value": 52
    },
    "quality": 0,
    "base-damage-min": 57,
    "base-damage-max": 73,
    "base-magic-damage-min": 0,
    "base-magic-damage-max": 0,
    "stats": {
      "intelligence": 0,
      "dexterity": 0,
      "strength": 0,
      "vitality": 0,
      "luck": 0,
      "energy-shield": 0,
      "magic-find": 0,
      "armor": 0,
      "attack": 0,
      "magic-attack": 0,
      "initiative": 8,
      "evasion": 0,
      "crit-chance": 6,
      "crit-damage": 0,
      "chaosDamage": 0,
      "magic-damage-fire": 0,
      "magic-damage-cold": 0,
      "magic-damage-lightning": 0,
      "damage-min": 57,
      "damage-max": 73,
      "magic-damage-min": 0,
      "magic-damage-max": 0,
      "resistances": {
        "fire": 0,
        "cold": 0,
        "lightning": 0,
        "chaos": 0
      }
    }
  },
  {
    "name": "Weltenspalter",
    "description": "Ein einziger Schlag dieser Klinge soll einst einen Berg gespalten haben.",
    "img-path": "imgs/items/weapon/worldsplitter.webp",
    "price": 2350,
    "armor-slot": "weapon-1",
    "tier": "5",
    "weapon-type": "schnitt",
    "hands": "2",
    "requirement": {
      "stat": "strength",
      "value": 60
    },
    "quality": 0,
    "base-damage-min": 80,
    "base-damage-max": 100,
    "base-magic-damage-min": 0,
    "base-magic-damage-max": 0,
    "stats": {
      "intelligence": 0,
      "dexterity": 0,
      "strength": 0,
      "vitality": 0,
      "luck": 0,
      "energy-shield": 0,
      "magic-find": 0,
      "armor": 0,
      "attack": 0,
      "magic-attack": 0,
      "initiative": 0,
      "evasion": 0,
      "crit-chance": 6,
      "crit-damage": 28,
      "chaosDamage": 0,
      "magic-damage-fire": 0,
      "magic-damage-cold": 0,
      "magic-damage-lightning": 0,
      "damage-min": 80,
      "damage-max": 100,
      "magic-damage-min": 0,
      "magic-damage-max": 0,
      "resistances": {
        "fire": 0,
        "cold": 0,
        "lightning": 0,
        "chaos": 0
      }
    }
  },
  {
    "name": "Kriegsgott-Streitkolben",
    "description": "Geweihte Waffe eines vergessenen Kriegsgottes.",
    "img-path": "imgs/items/weapon/wargod_mace.webp",
    "price": 1480,
    "armor-slot": "weapon-1",
    "tier": "5",
    "weapon-type": "stumpf",
    "hands": "1",
    "requirement": {
      "stat": "strength",
      "value": 52
    },
    "quality": 0,
    "base-damage-min": 60,
    "base-damage-max": 70,
    "base-magic-damage-min": 0,
    "base-magic-damage-max": 0,
    "stats": {
      "intelligence": 0,
      "dexterity": 0,
      "strength": 0,
      "vitality": 0,
      "luck": 0,
      "energy-shield": 0,
      "magic-find": 0,
      "armor": 0,
      "attack": 0,
      "magic-attack": 0,
      "initiative": 0,
      "evasion": 0,
      "crit-chance": 0,
      "crit-damage": 24,
      "chaosDamage": 0,
      "magic-damage-fire": 0,
      "magic-damage-cold": 0,
      "magic-damage-lightning": 0,
      "damage-min": 60,
      "damage-max": 70,
      "magic-damage-min": 0,
      "magic-damage-max": 0,
      "resistances": {
        "fire": 0,
        "cold": 0,
        "lightning": 0,
        "chaos": 0
      }
    }
  },
  {
    "name": "Apokalypsenhammer",
    "description": "Jeder Schlag hallt wie das Ende der Welt.",
    "img-path": "imgs/items/weapon/apocalypse_hammer.webp",
    "price": 2380,
    "armor-slot": "weapon-1",
    "tier": "5",
    "weapon-type": "stumpf",
    "hands": "2",
    "requirement": {
      "stat": "strength",
      "value": 60
    },
    "quality": 0,
    "base-damage-min": 84,
    "base-damage-max": 96,
    "base-magic-damage-min": 0,
    "base-magic-damage-max": 0,
    "stats": {
      "intelligence": 0,
      "dexterity": 0,
      "strength": 0,
      "vitality": 0,
      "luck": 0,
      "energy-shield": 0,
      "magic-find": 0,
      "armor": 0,
      "attack": 0,
      "magic-attack": 0,
      "initiative": 0,
      "evasion": 0,
      "crit-chance": 0,
      "crit-damage": 32,
      "chaosDamage": 14,
      "magic-damage-fire": 0,
      "magic-damage-cold": 0,
      "magic-damage-lightning": 0,
      "damage-min": 84,
      "damage-max": 96,
      "magic-damage-min": 0,
      "magic-damage-max": 0,
      "resistances": {
        "fire": 0,
        "cold": 0,
        "lightning": 0,
        "chaos": 0
      }
    }
  },
  {
    "name": "Todesstachel",
    "description": "Dünn wie eine Nadel, tödlich wie der Tod selbst.",
    "img-path": "imgs/items/weapon/deathsting_dagger.webp",
    "price": 1520,
    "armor-slot": "weapon-1",
    "tier": "5",
    "weapon-type": "stich",
    "hands": "1",
    "requirement": {
      "stat": "dexterity",
      "value": 52
    },
    "quality": 0,
    "base-damage-min": 45,
    "base-damage-max": 85,
    "base-magic-damage-min": 0,
    "base-magic-damage-max": 0,
    "stats": {
      "intelligence": 0,
      "dexterity": 0,
      "strength": 0,
      "vitality": 0,
      "luck": 0,
      "energy-shield": 0,
      "magic-find": 0,
      "armor": 0,
      "attack": 0,
      "magic-attack": 0,
      "initiative": 11,
      "evasion": 0,
      "crit-chance": 12,
      "crit-damage": 0,
      "chaosDamage": 7,
      "magic-damage-fire": 0,
      "magic-damage-cold": 0,
      "magic-damage-lightning": 0,
      "damage-min": 45,
      "damage-max": 85,
      "magic-damage-min": 0,
      "magic-damage-max": 0,
      "resistances": {
        "fire": 0,
        "cold": 0,
        "lightning": 0,
        "chaos": 0
      }
    }
  },
  {
    "name": "Himmelsbogen",
    "description": "Von Sturmwind getragene Pfeile treffen, wo immer man zielt.",
    "img-path": "imgs/items/weapon/skybow.webp",
    "price": 2300,
    "armor-slot": "weapon-1",
    "tier": "5",
    "weapon-type": "stich",
    "hands": "2",
    "requirement": {
      "stat": "dexterity",
      "value": 60
    },
    "quality": 0,
    "base-damage-min": 66,
    "base-damage-max": 112,
    "base-magic-damage-min": 0,
    "base-magic-damage-max": 0,
    "stats": {
      "intelligence": 0,
      "dexterity": 0,
      "strength": 0,
      "vitality": 0,
      "luck": 0,
      "energy-shield": 0,
      "magic-find": 0,
      "armor": 0,
      "attack": 0,
      "magic-attack": 0,
      "initiative": 16,
      "evasion": 0,
      "crit-chance": 9,
      "crit-damage": 0,
      "chaosDamage": 0,
      "magic-damage-fire": 0,
      "magic-damage-cold": 0,
      "magic-damage-lightning": 0,
      "damage-min": 66,
      "damage-max": 112,
      "magic-damage-min": 0,
      "magic-damage-max": 0,
      "resistances": {
        "fire": 0,
        "cold": 0,
        "lightning": 0,
        "chaos": 0
      }
    }
  },
  {
    "name": "Stab der Urgewalt",
    "description": "Enthält einen Splitter uralter, nicht klassifizierbarer Magie.",
    "img-path": "imgs/items/weapon/primalforce_staff.webp",
    "price": 1550,
    "armor-slot": "weapon-1",
    "tier": "5",
    "weapon-type": "magie",
    "magic-damage-type": "cold",
    "hands": "1",
    "requirement": {
      "stat": "intelligence",
      "value": 52
    },
    "quality": 0,
    "base-damage-min": 0,
    "base-damage-max": 0,
    "base-magic-damage-min": 54,
    "base-magic-damage-max": 76,
    "stats": {
      "intelligence": 0,
      "dexterity": 0,
      "strength": 0,
      "vitality": 0,
      "luck": 6,
      "energy-shield": 0,
      "magic-find": 16,
      "armor": 0,
      "attack": 0,
      "magic-attack": 0,
      "initiative": 0,
      "evasion": 0,
      "crit-chance": 0,
      "crit-damage": 0,
      "chaosDamage": 0,
      "magic-damage-fire": 0,
      "magic-damage-cold": 16,
      "magic-damage-lightning": 0,
      "damage-min": 0,
      "damage-max": 0,
      "magic-damage-min": 54,
      "magic-damage-max": 76,
      "resistances": {
        "fire": 0,
        "cold": 0,
        "lightning": 0,
        "chaos": 0
      }
    }
  },
  {
    "name": "Zepter des Weltuntergangs",
    "description": "Das letzte Werk eines Erzmagiers, der die Konsequenzen ignorierte.",
    "img-path": "imgs/items/weapon/doomsday_scepter.webp",
    "price": 2400,
    "armor-slot": "weapon-1",
    "tier": "5",
    "weapon-type": "magie",
    "magic-damage-type": "chaos",
    "hands": "2",
    "requirement": {
      "stat": "intelligence",
      "value": 60
    },
    "quality": 0,
    "base-damage-min": 0,
    "base-damage-max": 0,
    "base-magic-damage-min": 74,
    "base-magic-damage-max": 106,
    "stats": {
      "intelligence": 0,
      "dexterity": 0,
      "strength": 0,
      "vitality": 0,
      "luck": 0,
      "energy-shield": 0,
      "magic-find": 18,
      "armor": 0,
      "attack": 0,
      "magic-attack": 0,
      "initiative": 0,
      "evasion": 0,
      "crit-chance": 0,
      "crit-damage": 0,
      "chaosDamage": 16,
      "magic-damage-fire": 0,
      "magic-damage-cold": 0,
      "magic-damage-lightning": 0,
      "damage-min": 0,
      "damage-max": 0,
      "magic-damage-min": 74,
      "magic-damage-max": 106,
      "resistances": {
        "fire": 0,
        "cold": 0,
        "lightning": 0,
        "chaos": 0
      }
    }
  }
]
